{
  "__AUTOGENERATED_FILE_DO_NOT_MODIFY_THIS_FILE_MANUALLY": "THERE_IS_NO_DATA_ONLY_ZUUL",
  "__INPUT_ARTIFACTS_HASH": -2137025570,
  "__RESOLVED_ARTIFACTS_HASH": -1182922402,
  "artifacts": {
    "com.google.code.findbugs:jsr305": {
      "shasums": {
        "jar": "766ad2a0783f2687962c8ad74ceecc38a28b9f72a2d085ee438b7813e928d0c7",
        "sources": "1c9e85e272d0708c6a591dc74828c71603053b48cc75ae83cce56912a2aa063b"
      },
      "version": "3.0.2"
    },
    "com.google.errorprone:error_prone_annotations": {
      "shasums": {
        "jar": "cd5257c08a246cf8628817ae71cb822be192ef91f6881ca4a3fcff4f1de1cff3",
        "sources": "e38921f918b8ad8eabd12bc61de426fa96c72de077054e9147d2f9fe7c648923"
      },
      "version": "2.7.1"
    },
    "com.google.guava:failureaccess": {
      "shasums": {
        "jar": "a171ee4c734dd2da837e4b16be9df4661afab72a41adaf31eb84dfdaf936ca26",
        "sources": "092346eebbb1657b51aa7485a246bf602bb464cc0b0e2e1c7e7201fadce1e98f"
      },
      "version": "1.0.1"
    },
    "com.google.guava:guava": {
      "shasums": {
        "jar": "d5be94d65e87bd219fb3193ad1517baa55a3b88fc91d21cf735826ab5af087b9",
        "sources": "fc0fb66f315f10b8713fc43354936d3649a8ad63f789d42fd7c3e55ecf72e092"
      },
      "version": "31.0.1-jre"
    },
    "com.google.guava:listenablefuture": {
      "shasums": {
        "jar": "b372a037d4230aa57fbeffdef30fd6123f9c0c2db85d0aced00c91b974f33f99",
        "sources": null
      },
      "version": "9999.0-empty-to-avoid-conflict-with-guava"
    },
    "com.google.j2objc:j2objc-annotations": {
      "shasums": {
        "jar": "21af30c92267bd6122c0e0b4d20cccb6641a37eaf956c6540ec471d584e64a7b",
        "sources": "ba4df669fec153fa4cd0ef8d02c6d3ef0702b7ac4cabe080facf3b6e490bb972"
      },
      "version": "1.3"
    },
    "com.googlecode.javaewah:JavaEWAH": {
      "shasums": {
        "jar": "3ecf8b2c602314341f5a2ace171ed04fc86f2d4ddf762180656e9b71134ae68f",
        "sources": "e4ee176218d910edd5d3d06e08bd5385ba312886bcf4574f12f59dbee37fc5a2"
      },
      "version": "1.1.7"
    },
    "junit:junit": {
      "shasums": {
        "jar": "59721f0805e223d84b90677887d9ff567dc534d7c502ca903c0c2b17f05c116a",
        "sources": "9f43fea92033ad82bcad2ae44cec5c82abc9d6ee4b095cab921d11ead98bf2ff"
      },
      "version": "4.12"
    },
    "org.checkerframework:checker-qual": {
      "shasums": {
        "jar": "ff10785ac2a357ec5de9c293cb982a2cbb605c0309ea4cc1cb9b9bc6dbe7f3cb",
        "sources": "fd99a45195ed893803624d1030387056a96601013f5e61ccabd79abb4ddfa876"
      },
      "version": "3.12.0"
    },
    "org.eclipse.jgit:org.eclipse.jgit": {
      "shasums": {
        "jar": "b0f012105d67729a67c7fde546b6e89580f7ddc5bd73c6c7bae7084c50e36a37",
        "sources": "23b4f2debe38b2e18cb925ada6639eb78cc029243060f8f8c080ba3e0e70ab71"
      },
      "version": "5.11.0.202103091610-r"
    },
    "org.hamcrest:hamcrest-all": {
      "shasums": {
        "jar": "4877670629ab96f34f5f90ab283125fcd9acb7e683e66319a68be6eb2cca60de",
        "sources": "c53535c3d25b5bf0b00a324a5583c7dd2fed0fa6d1bbc622e2dec460c24faab3"
      },
      "version": "1.3"
    },
    "org.hamcrest:hamcrest-core": {
      "shasums": {
        "jar": "66fdef91e9739348df7a096aa384a5685f4e875584cce89386a7a47251c4d8e9",
        "sources": "e223d2d8fbafd66057a8848cc94222d63c3cedd652cc48eddc0ab5c39c0f84df"
      },
      "version": "1.3"
    },
    "org.slf4j:slf4j-api": {
      "shasums": {
        "jar": "cdba07964d1bb40a0761485c6b1e8c2f8fd9eb1d19c53928ac0d7f9510105c57",
        "sources": "9ee459644577590fed7ea94afae781fa3cc9311d4553faee8a3219ffbd7cc386"
      },
      "version": "1.7.30"
    }
  },
  "dependencies": {
    "com.google.guava:guava": [
      "com.google.code.findbugs:jsr305",
      "com.google.errorprone:error_prone_annotations",
      "com.google.guava:failureaccess",
      "com.google.guava:listenablefuture",
      "com.google.j2objc:j2objc-annotations",
      "org.checkerframework:checker-qual"
    ],
    "junit:junit": [
      "org.hamcrest:hamcrest-core"
    ],
    "org.eclipse.jgit:org.eclipse.jgit": [
      "com.googlecode.javaewah:JavaEWAH",
      "org.slf4j:slf4j-api"
    ]
  },
  "packages": {
    "com.google.code.findbugs:jsr305": [
      "javax.annotation",
      "javax.annotation.concurrent",
      "javax.annotation.meta"
    ],
    "com.google.errorprone:error_prone_annotations": [
      "com.google.errorprone.annotations",
      "com.google.errorprone.annotations.concurrent"
    ],
    "com.google.guava:failureaccess": [
      "com.google.common.util.concurrent.internal"
    ],
    "com.google.guava:guava": [
      "com.google.common.annotations",
      "com.google.common.base",
      "com.google.common.base.internal",
      "com.google.common.cache",
      "com.google.common.collect",
      "com.google.common.escape",
      "com.google.common.eventbus",
      "com.google.common.graph",
      "com.google.common.hash",
      "com.google.common.html",
      "com.google.common.io",
      "com.google.common.math",
      "com.google.common.net",
      "com.google.common.primitives",
      "com.google.common.reflect",
      "com.google.common.util.concurrent",
      "com.google.common.xml",
      "com.google.thirdparty.publicsuffix"
    ],
    "com.google.j2objc:j2objc-annotations": [
      "com.google.j2objc.annotations"
    ],
    "com.googlecode.javaewah:JavaEWAH": [
      "com.googlecode.javaewah",
      "com.googlecode.javaewah.datastructure",
      "com.googlecode.javaewah.symmetric",
      "com.googlecode.javaewah32",
      "com.googlecode.javaewah32.symmetric"
    ],
    "junit:junit": [
      "junit.extensions",
      "junit.framework",
      "junit.runner",
      "junit.textui",
      "org.junit",
      "org.junit.experimental",
      "org.junit.experimental.categories",
      "org.junit.experimental.max",
      "org.junit.experimental.results",
      "org.junit.experimental.runners",
      "org.junit.experimental.theories",
      "org.junit.experimental.theories.internal",
      "org.junit.experimental.theories.suppliers",
      "org.junit.internal",
      "org.junit.internal.builders",
      "org.junit.internal.matchers",
      "org.junit.internal.requests",
      "org.junit.internal.runners",
      "org.junit.internal.runners.model",
      "org.junit.internal.runners.rules",
      "org.junit.internal.runners.statements",
      "org.junit.matchers",
      "org.junit.rules",
      "org.junit.runner",
      "org.junit.runner.manipulation",
      "org.junit.runner.notification",
      "org.junit.runners",
      "org.junit.runners.model",
      "org.junit.runners.parameterized",
      "org.junit.validator"
    ],
    "org.checkerframework:checker-qual": [
      "org.checkerframework.checker.builder.qual",
      "org.checkerframework.checker.calledmethods.qual",
      "org.checkerframework.checker.compilermsgs.qual",
      "org.checkerframework.checker.fenum.qual",
      "org.checkerframework.checker.formatter.qual",
      "org.checkerframework.checker.guieffect.qual",
      "org.checkerframework.checker.i18n.qual",
      "org.checkerframework.checker.i18nformatter.qual",
      "org.checkerframework.checker.index.qual",
      "org.checkerframework.checker.initialization.qual",
      "org.checkerframework.checker.interning.qual",
      "org.checkerframework.checker.lock.qual",
      "org.checkerframework.checker.nullness.qual",
      "org.checkerframework.checker.optional.qual",
      "org.checkerframework.checker.propkey.qual",
      "org.checkerframework.checker.regex.qual",
      "org.checkerframework.checker.signature.qual",
      "org.checkerframework.checker.signedness.qual",
      "org.checkerframework.checker.tainting.qual",
      "org.checkerframework.checker.units.qual",
      "org.checkerframework.common.aliasing.qual",
      "org.checkerframework.common.initializedfields.qual",
      "org.checkerframework.common.reflection.qual",
      "org.checkerframework.common.returnsreceiver.qual",
      "org.checkerframework.common.subtyping.qual",
      "org.checkerframework.common.util.report.qual",
      "org.checkerframework.common.value.qual",
      "org.checkerframework.dataflow.qual",
      "org.checkerframework.framework.qual"
    ],
    "org.eclipse.jgit:org.eclipse.jgit": [
      "org.eclipse.jgit.annotations",
      "org.eclipse.jgit.api",
      "org.eclipse.jgit.api.errors",
      "org.eclipse.jgit.attributes",
      "org.eclipse.jgit.blame",
      "org.eclipse.jgit.diff",
      "org.eclipse.jgit.dircache",
      "org.eclipse.jgit.errors",
      "org.eclipse.jgit.events",
      "org.eclipse.jgit.fnmatch",
      "org.eclipse.jgit.gitrepo",
      "org.eclipse.jgit.gitrepo.internal",
      "org.eclipse.jgit.hooks",
      "org.eclipse.jgit.ignore",
      "org.eclipse.jgit.ignore.internal",
      "org.eclipse.jgit.internal",
      "org.eclipse.jgit.internal.fsck",
      "org.eclipse.jgit.internal.revwalk",
      "org.eclipse.jgit.internal.storage.dfs",
      "org.eclipse.jgit.internal.storage.file",
      "org.eclipse.jgit.internal.storage.io",
      "org.eclipse.jgit.internal.storage.pack",
      "org.eclipse.jgit.internal.storage.reftable",
      "org.eclipse.jgit.internal.submodule",
      "org.eclipse.jgit.internal.transport.connectivity",
      "org.eclipse.jgit.internal.transport.http",
      "org.eclipse.jgit.internal.transport.parser",
      "org.eclipse.jgit.internal.transport.ssh",
      "org.eclipse.jgit.lib",
      "org.eclipse.jgit.lib.internal",
      "org.eclipse.jgit.logging",
      "org.eclipse.jgit.merge",
      "org.eclipse.jgit.nls",
      "org.eclipse.jgit.notes",
      "org.eclipse.jgit.patch",
      "org.eclipse.jgit.revplot",
      "org.eclipse.jgit.revwalk",
      "org.eclipse.jgit.revwalk.filter",
      "org.eclipse.jgit.storage.file",
      "org.eclipse.jgit.storage.pack",
      "org.eclipse.jgit.submodule",
      "org.eclipse.jgit.transport",
      "org.eclipse.jgit.transport.http",
      "org.eclipse.jgit.transport.resolver",
      "org.eclipse.jgit.treewalk",
      "org.eclipse.jgit.treewalk.filter",
      "org.eclipse.jgit.util",
      "org.eclipse.jgit.util.io",
      "org.eclipse.jgit.util.sha1",
      "org.eclipse.jgit.util.time"
    ],
    "org.hamcrest:hamcrest-all": [
      "org.hamcrest",
      "org.hamcrest.beans",
      "org.hamcrest.collection",
      "org.hamcrest.core",
      "org.hamcrest.generator",
      "org.hamcrest.generator.config",
      "org.hamcrest.generator.qdox",
      "org.hamcrest.generator.qdox.ant",
      "org.hamcrest.generator.qdox.directorywalker",
      "org.hamcrest.generator.qdox.junit",
      "org.hamcrest.generator.qdox.model",
      "org.hamcrest.generator.qdox.model.annotation",
      "org.hamcrest.generator.qdox.model.util",
      "org.hamcrest.generator.qdox.parser",
      "org.hamcrest.generator.qdox.parser.impl",
      "org.hamcrest.generator.qdox.parser.structs",
      "org.hamcrest.generator.qdox.tools",
      "org.hamcrest.integration",
      "org.hamcrest.internal",
      "org.hamcrest.number",
      "org.hamcrest.object",
      "org.hamcrest.text",
      "org.hamcrest.xml"
    ],
    "org.hamcrest:hamcrest-core": [
      "org.hamcrest",
      "org.hamcrest.core",
      "org.hamcrest.internal"
    ],
    "org.slf4j:slf4j-api": [
      "org.slf4j",
      "org.slf4j.event",
      "org.slf4j.helpers",
      "org.slf4j.spi"
    ]
  },
  "repositories": {
    "https://repo1.maven.org/maven2/": [
      "com.google.code.findbugs:jsr305",
      "com.google.code.findbugs:jsr305:jar:sources",
      "com.google.errorprone:error_prone_annotations",
      "com.google.errorprone:error_prone_annotations:jar:sources",
      "com.google.guava:failureaccess",
      "com.google.guava:failureaccess:jar:sources",
      "com.google.guava:guava",
      "com.google.guava:guava:jar:sources",
      "com.google.guava:listenablefuture",
      "com.google.j2objc:j2objc-annotations",
      "com.google.j2objc:j2objc-annotations:jar:sources",
      "com.googlecode.javaewah:JavaEWAH",
      "com.googlecode.javaewah:JavaEWAH:jar:sources",
      "junit:junit",
      "junit:junit:jar:sources",
      "org.checkerframework:checker-qual",
      "org.checkerframework:checker-qual:jar:sources",
      "org.eclipse.jgit:org.eclipse.jgit",
      "org.eclipse.jgit:org.eclipse.jgit:jar:sources",
      "org.hamcrest:hamcrest-all",
      "org.hamcrest:hamcrest-all:jar:sources",
      "org.hamcrest:hamcrest-core",
      "org.hamcrest:hamcrest-core:jar:sources",
      "org.slf4j:slf4j-api",
      "org.slf4j:slf4j-api:jar:sources"
    ]
  },
  "services": {},
  "skipped": [
    "com.google.guava:listenablefuture:jar:sources"
  ],
  "version": "2"
}
